nataili_blip/__init__.py
nataili_blip/caption.py
nataili_blip/cli.py
nataili_blip/med_config.json
nataili_blip/models.json
nataili_blip/ui.py
nataili_blip/model_manager/__init__.py
nataili_blip/model_manager/base.py
nataili_blip/model_manager/blip.py
nataili_blip/util/__init__.py
nataili_blip/util/blip.py
nataili_blip/util/logger.py
nataili_blip/util/med.py
nataili_blip/util/performance.py
nataili_blip/util/vit.py
nataili_blip-0.0.2.dist-info/LICENSE
nataili_blip-0.0.2.dist-info/METADATA
nataili_blip-0.0.2.dist-info/WHEEL
nataili_blip-0.0.2.dist-info/entry_points.txt
nataili_blip-0.0.2.dist-info/top_level.txt
nataili_blip-0.0.2.dist-info/RECORD
