Metadata-Version: 2.1
Name: nataili-blip
Version: 0.0.2
Summary: Nataili BLIP: A Python library for captioning images with BLIP
Author-email: hlky <goto@github.com>
License: GNU AFFERO GENERAL PUBLIC LICENSE
Project-URL: Homepage, https://github.com/Sygil-Dev/nataili_blip
Project-URL: Bug Tracker, https://github.com/Sygil-Dev/nataili_blip/issues
Classifier: Programming Language :: Python :: 3
Classifier: License :: OSI Approved :: GNU Affero General Public License v3
Classifier: Operating System :: OS Independent
Requires-Python: >=3.8
License-File: LICENSE
Requires-Dist: transformers (==4.21.3)
Requires-Dist: GitPython (>=3.1.24)
Requires-Dist: loguru (>=0.5.3)
Requires-Dist: numpy (>=1.21.2)
Requires-Dist: timm (>=0.6.0)
Requires-Dist: fairscale (>=0.4.0)
Requires-Dist: tqdm (>=4.62.3)
Requires-Dist: requests (>=2.26.0)
Requires-Dist: click (>=8.0.1)
Requires-Dist: importlib-resources (>=1.1.0) ; python_version < "3.9"
